async_rate_limiter/RateLimiter.py
async_rate_limiter/Reuseables.py
async_rate_limiter/WeightedRateLimiter.py
async_rate_limiter/__init__.py
async_serialized_rate_limiter-0.2.2.dist-info/METADATA
async_serialized_rate_limiter-0.2.2.dist-info/WHEEL
async_serialized_rate_limiter-0.2.2.dist-info/top_level.txt
async_serialized_rate_limiter-0.2.2.dist-info/RECORD
