Metadata-Version: 2.4
Name: async-serialized-rate-limiter
Version: 0.2.2
Summary: A strict asyncio rate limiter with serialized execution and sliding-window guarantees
Author-email: sumitdhyani <sumitdhyani1@gmail.com>
Keywords: asyncio,rate-limiter,rate limiting,sliding window,throttling
Classifier: Programming Language :: Python :: 3
Classifier: Programming Language :: Python :: 3 :: Only
Classifier: Framework :: AsyncIO
Classifier: Intended Audience :: Developers
Classifier: Topic :: Software Development :: Libraries
Classifier: Topic :: Utilities
Requires-Python: >=3.8
